heist/conf.py
heist/scripts.py
heist/version.py
heist/artifact/init.py
heist/artifact/contracts/init.py
heist/heist/init.py
heist/heist/test.py
heist/heist/recursive_contracts/init.py
heist/output/heist.py
heist/roster/clustershell.py
heist/roster/flat.py
heist/roster/init.py
heist/roster/scan.py
heist/roster/contracts/init.py
heist/service/init.py
heist/service/raw.py
heist/service/systemd.py
heist/service/win_service.py
heist/service/contracts/init.py
heist/tool/artifacts.py
heist/tool/path.py
heist/tool/system.py
heist/tunnel/asyncssh.py
heist/tunnel/contracts/init.py
heist-7.0.2.dist-info/LICENSE
heist-7.0.2.dist-info/METADATA
heist-7.0.2.dist-info/WHEEL
heist-7.0.2.dist-info/entry_points.txt
heist-7.0.2.dist-info/top_level.txt
heist-7.0.2.dist-info/RECORD
