Metadata-Version: 2.1
Name: heist
Version: 7.0.2
Summary: Pluggable ephemeral software tunneling and delivery system
Home-page: https://gitlab.com/saltstack/pop/heist
Author: VMware Inc.
Author-email: 
Classifier: Operating System :: OS Independent
Classifier: Programming Language :: Python :: 3.9
Classifier: Programming Language :: Python :: 3.10
Classifier: Development Status :: 5 - Production/Stable
Requires-Python: >=3.9
License-File: LICENSE
Requires-Dist: aiohttp >=3.0.1
Requires-Dist: asyncssh >=1.18.0
Requires-Dist: pop >=23.1.0
Requires-Dist: pop-config >=12.0.1
Requires-Dist: rend >=6.0.0
Requires-Dist: ClusterShell >=1.8.1
